eufylife_ble_client/__init__.py
eufylife_ble_client/auth_handler.py
eufylife_ble_client/client.py
eufylife_ble_client/exceptions.py
eufylife_ble_client/models.py
eufylife_ble_client/util.py
eufylife_ble_client-0.1.9.dist-info/METADATA
eufylife_ble_client-0.1.9.dist-info/WHEEL
eufylife_ble_client-0.1.9.dist-info/RECORD
