Metadata-Version: 2.1
Name: eufylife-ble-client
Version: 0.1.9
Summary: A library to communicate with EufyLife Bluetooth devices.
Home-page: https://github.com/bdr99/eufylife-ble-client
License: MIT
Author: Brandon Rothweiler
Author-email: brandonrothweiler@gmail.com
Requires-Python: >=3.9,<4.0
Classifier: License :: OSI Approved :: MIT License
Classifier: Programming Language :: Python :: 3
Classifier: Programming Language :: Python :: 3.9
Classifier: Programming Language :: Python :: 3.10
Classifier: Programming Language :: Python :: 3.11
Classifier: Programming Language :: Python :: 3.12
Requires-Dist: bleak (>=0.19.0)
Requires-Dist: bleak-retry-connector (>=2.3.0)
Requires-Dist: cryptography (>=39.0)
